{"name":"Rachiopy","tagline":"","body":"Rachiopy\r\n========\r\nThis python package provides a interface to the Rachio public API.\r\n\r\nUsage\r\n-----\r\n```python\r\nfrom rachiopy import Rachio\r\n\r\nr = Rachio(\"authtoken\")\r\n\r\nr.person.getInfo()\r\n```\r\n\r\nCommands\r\n--------\r\n### Person\r\n\r\n`r.person.getInfo()`\r\n\r\n`r.person.get(id)`\r\n\r\n### Device\r\n\r\n`r.device.get(id)`\r\n\r\n`r.device.getCurrentSchedule(id)`\r\n\r\n`r.device.getEvent(id, starttime, endtime)`\r\n\r\n`r.device.getScheduleItem(id)`\r\n\r\n`r.device.getForecast(self, id, units)`\r\n\r\n`r.device.stopWater(id)`\r\n\r\n`r.device.rainDelay(id, duration)`\r\n\r\n`r.device.on(id)`\r\n\r\n`r.device.off(id)`\r\n\r\n### Zone\r\n\r\n`r.zone.start(id, duration)`\r\n\r\n`r.zone.startMultiple(zones)`\r\n\r\n### Schedulerule\r\n\r\n`r.schedulerule.skip(id)`\r\n\r\n`r.schedulerule.start(id)`\r\n\r\n`r.schedulerule.seasonalAdjustment(id, adjustment)`\r\n\r\n### Notification\r\n\r\n`r.notification.getWebhookEventType()`\r\n\r\n`r.notification.getDeviceWebhook(id)`\r\n\r\n`r.notification.postWebhook(webhook)`\r\n\r\n`r.notification.putWebhook(webhook)`\r\n\r\n`r.notification.deleteWebhook(id)`\r\n","google":"","note":"Don't delete this file! It's used internally to help with page regeneration."}